setup.py
RouteFS.egg-info/PKG-INFO
RouteFS.egg-info/SOURCES.txt
RouteFS.egg-info/dependency_links.txt
RouteFS.egg-info/requires.txt
RouteFS.egg-info/top_level.txt
routefs/__init__.py
routefs/dictfs.py
routefs/examples/__init__.py
routefs/examples/dictexfs.py
routefs/examples/homefs.py
routefs/examples/pyhesiodfs.py