Metadata-Version: 1.0
Name: RouteFS
Version: 1.1.1
Summary: RouteFS: A FUSE API wrapper based on URL routing
Home-page: http://github.com/ebroder/python-routefs/wikis
Author: Evan Broder
Author-email: broder@mit.edu
License: MPL, GPL
Platform: UNKNOWN
Classifier: Development Status :: 5 - Production/Stable
Classifier: Environment :: Plugins
Classifier: Environment :: No Input/Output (Daemon)
Classifier: Intended Audience :: Developers
Classifier: Intended Audience :: System Administrators
Classifier: License :: OSI Approved :: GNU General Public License (GPL)
Classifier: License :: OSI Approved :: Mozilla Public License 1.1 (MPL 1.1)
Classifier: License :: DFSG approved
Classifier: Operating System :: MacOS :: MacOS X
Classifier: Operating System :: POSIX
Classifier: Programming Language :: Python
